oidcauthlib/__init__.py
oidcauthlib/py.typed
oidcauthlib/auth/__init__.py
oidcauthlib/auth/auth_helper.py
oidcauthlib/auth/auth_manager.py
oidcauthlib/auth/fastapi_auth_manager.py
oidcauthlib/auth/token_reader.py
oidcauthlib/auth/cache/__init__.py
oidcauthlib/auth/cache/oauth_cache.py
oidcauthlib/auth/cache/oauth_memory_cache.py
oidcauthlib/auth/cache/oauth_mongo_cache.py
oidcauthlib/auth/config/__init__.py
oidcauthlib/auth/config/auth_config.py
oidcauthlib/auth/config/auth_config_reader.py
oidcauthlib/auth/exceptions/__init__.py
oidcauthlib/auth/exceptions/authorization_bearer_token_expired_exception.py
oidcauthlib/auth/exceptions/authorization_bearer_token_invalid_exception.py
oidcauthlib/auth/exceptions/authorization_bearer_token_missing_exception.py
oidcauthlib/auth/exceptions/authorization_needed_exception.py
oidcauthlib/auth/middleware/__init__.py
oidcauthlib/auth/middleware/request_scope_middleware.py
oidcauthlib/auth/middleware/token_reader_middleware.py
oidcauthlib/auth/models/__init__.py
oidcauthlib/auth/models/auth.py
oidcauthlib/auth/models/base_db_model.py
oidcauthlib/auth/models/cache_item.py
oidcauthlib/auth/models/client_key_set.py
oidcauthlib/auth/models/token.py
oidcauthlib/auth/repository/__init__.py
oidcauthlib/auth/repository/base_repository.py
oidcauthlib/auth/repository/repository_factory.py
oidcauthlib/auth/repository/memory/__init__.py
oidcauthlib/auth/repository/memory/memory_repository.py
oidcauthlib/auth/repository/mongo/__init__.py
oidcauthlib/auth/repository/mongo/mongo_repository.py
oidcauthlib/auth/routers/__init__.py
oidcauthlib/auth/routers/auth_router.py
oidcauthlib/auth/well_known_configuration/__init__.py
oidcauthlib/auth/well_known_configuration/well_known_configuration_cache.py
oidcauthlib/auth/well_known_configuration/well_known_configuration_cache_result.py
oidcauthlib/auth/well_known_configuration/well_known_configuration_manager.py
oidcauthlib/container/__init__.py
oidcauthlib/container/container_registry.py
oidcauthlib-2.0.10.dist-info/licenses/LICENSE
oidcauthlib-2.0.10.dist-info/METADATA
oidcauthlib-2.0.10.dist-info/WHEEL
oidcauthlib-2.0.10.dist-info/top_level.txt
oidcauthlib-2.0.10.dist-info/RECORD
