Metadata-Version: 2.4
Name: oidcauthlib
Version: 2.0.10
Summary: oidcauthlib
Home-page: https://github.com/icanbwell/oidc-auth-lib
Author: Imran Qureshi
Author-email: imran.qureshi@bwell.com
Classifier: Development Status :: 4 - Beta
Classifier: Programming Language :: Python :: 3
Classifier: License :: OSI Approved :: Apache Software License
Classifier: Operating System :: OS Independent
Requires-Python: >=3.12
License-File: LICENSE
Requires-Dist: httpx>=0.27.2
Requires-Dist: authlib>=1.6.4
Requires-Dist: joserfc>=1.4.3
Requires-Dist: pydantic<3.0.0,>=2.0
Requires-Dist: pymongo[snappy]>=4.15.3
Requires-Dist: python-snappy>=0.7.3
Requires-Dist: fastapi>=0.115.8
Requires-Dist: starlette>=0.49.1
Requires-Dist: py-key-value-aio[memory,mongodb,pydantic,redis]>=0.3.0
Requires-Dist: opentelemetry-api>=1.39.1
Dynamic: author
Dynamic: author-email
Dynamic: classifier
Dynamic: description
Dynamic: description-content-type
Dynamic: home-page
Dynamic: license-file
Dynamic: requires-dist
Dynamic: requires-python
Dynamic: summary
